trame_slicer/__init__.py
trame_slicer/core/__init__.py
trame_slicer/core/display_manager.py
trame_slicer/core/io_manager.py
trame_slicer/core/layout_manager.py
trame_slicer/core/markups_logic.py
trame_slicer/core/segmentation_editor.py
trame_slicer/core/slicer_app.py
trame_slicer/core/view_manager.py
trame_slicer/core/volume_property.py
trame_slicer/core/volume_rendering.py
trame_slicer/core/volume_window_level.py
trame_slicer/core/volumes_reader.py
trame_slicer/rca_view/__init__.py
trame_slicer/rca_view/rca_view_factory.py
trame_slicer/resources/__init__.py
trame_slicer/resources/presets.xml
trame_slicer/resources/presets_icons/CT-AAA.png
trame_slicer/resources/presets_icons/CT-AAA2.png
trame_slicer/resources/presets_icons/CT-Air.png
trame_slicer/resources/presets_icons/CT-Bone.png
trame_slicer/resources/presets_icons/CT-Bones.png
trame_slicer/resources/presets_icons/CT-Cardiac.png
trame_slicer/resources/presets_icons/CT-Cardiac2.png
trame_slicer/resources/presets_icons/CT-Cardiac3.png
trame_slicer/resources/presets_icons/CT-Chest-Contrast-Enhanced.png
trame_slicer/resources/presets_icons/CT-Chest-Vessels.png
trame_slicer/resources/presets_icons/CT-Coronary-Arteries-2.png
trame_slicer/resources/presets_icons/CT-Coronary-Arteries-3.png
trame_slicer/resources/presets_icons/CT-Coronary-Arteries.png
trame_slicer/resources/presets_icons/CT-Cropped-Volume-Bone.png
trame_slicer/resources/presets_icons/CT-Fat.png
trame_slicer/resources/presets_icons/CT-Liver-Vasculature.png
trame_slicer/resources/presets_icons/CT-Lung.png
trame_slicer/resources/presets_icons/CT-MIP.png
trame_slicer/resources/presets_icons/CT-Muscle.png
trame_slicer/resources/presets_icons/CT-Pulmonary-Arteries.png
trame_slicer/resources/presets_icons/CT-Soft-Tissue.png
trame_slicer/resources/presets_icons/CT-X-ray.png
trame_slicer/resources/presets_icons/DTI-FA-Brain.png
trame_slicer/resources/presets_icons/MR-Angio.png
trame_slicer/resources/presets_icons/MR-Default.png
trame_slicer-1.7.2.dist-info/METADATA
trame_slicer-1.7.2.dist-info/WHEEL
trame_slicer-1.7.2.dist-info/licenses/LICENSE
trame_slicer-1.7.2.dist-info/RECORD
