Metadata-Version: 2.4
Name: trame-slicer
Version: 1.7.2
Summary: trame-slicer library
Author-email: Alexy Pellegrini <alexy.pellegrini@kitware.com>, Jonathan Bouyer <jonathan.bouyer@kitware.com>, Thibault Pelletier <thibault.pelletier@kitware.com>
License: Apache 2.0 License
License-File: LICENSE
Keywords: 3DSlicer,Application,Framework,Interactive,Medical,Python,Web
Classifier: Development Status :: 4 - Beta
Classifier: Environment :: Web Environment
Classifier: License :: OSI Approved :: Apache Software License
Classifier: Natural Language :: English
Classifier: Operating System :: OS Independent
Classifier: Programming Language :: JavaScript
Classifier: Programming Language :: Python :: 3 :: Only
Classifier: Topic :: Software Development :: Libraries :: Application Frameworks
Classifier: Topic :: Software Development :: Libraries :: Python Modules
Requires-Python: >=3.9
Requires-Dist: itk
Requires-Dist: lxml
Requires-Dist: pillow
Requires-Dist: pillow-avif-plugin
Requires-Dist: py-undo-stack
Requires-Dist: pydicom
Requires-Dist: trame
Requires-Dist: trame-client>=3.11.2
Requires-Dist: trame-rca>=2.2.1
Requires-Dist: trame-server>=3.6.3
Requires-Dist: trame-vtk
Requires-Dist: trame-vuetify
Requires-Dist: webcolors
Provides-Extra: dev
Requires-Dist: async-timeout; extra == 'dev'
Requires-Dist: nox; extra == 'dev'
Requires-Dist: pixelmatch; extra == 'dev'
Requires-Dist: pytest; extra == 'dev'
Requires-Dist: pytest-asyncio; extra == 'dev'
Requires-Dist: pytest-cov; extra == 'dev'
Requires-Dist: pytest-playwright; extra == 'dev'
Requires-Dist: pytest-xprocess; extra == 'dev'
Provides-Extra: docs
Requires-Dist: myst-parser>=4; extra == 'docs'
Requires-Dist: sphinx-autodoc-typehints; extra == 'docs'
Requires-Dist: sphinx-rtd-theme; extra == 'docs'
Requires-Dist: sphinx<9,>=8; extra == 'docs'
Requires-Dist: sphinxcontrib-mermaid; extra == 'docs'
Requires-Dist: vtk==9.4.0; extra == 'docs'
